odoo/addons/base_vat_optional_vies/README.rst
odoo/addons/base_vat_optional_vies/__init__.py
odoo/addons/base_vat_optional_vies/__manifest__.py
odoo/addons/base_vat_optional_vies/i18n/.gitkeep
odoo/addons/base_vat_optional_vies/i18n/base_vat_optional_vies.pot
odoo/addons/base_vat_optional_vies/i18n/es.po
odoo/addons/base_vat_optional_vies/i18n/fr.po
odoo/addons/base_vat_optional_vies/i18n/hr.po
odoo/addons/base_vat_optional_vies/i18n/pt.po
odoo/addons/base_vat_optional_vies/models/__init__.py
odoo/addons/base_vat_optional_vies/models/res_config_settings.py
odoo/addons/base_vat_optional_vies/models/res_partner.py
odoo/addons/base_vat_optional_vies/readme/CONFIGURE.rst
odoo/addons/base_vat_optional_vies/readme/CONTRIBUTORS.rst
odoo/addons/base_vat_optional_vies/readme/DESCRIPTION.rst
odoo/addons/base_vat_optional_vies/readme/USAGE.rst
odoo/addons/base_vat_optional_vies/static/description/icon.png
odoo/addons/base_vat_optional_vies/static/description/index.html
odoo/addons/base_vat_optional_vies/tests/__init__.py
odoo/addons/base_vat_optional_vies/tests/test_config_settings.py
odoo/addons/base_vat_optional_vies/tests/test_res_partner.py
odoo/addons/base_vat_optional_vies/views/res_config_settings_views.xml
odoo/addons/base_vat_optional_vies/views/res_partner_view.xml
odoo14_addon_base_vat_optional_vies-14.0.2.1.0.dist-info/METADATA
odoo14_addon_base_vat_optional_vies-14.0.2.1.0.dist-info/WHEEL
odoo14_addon_base_vat_optional_vies-14.0.2.1.0.dist-info/top_level.txt
odoo14_addon_base_vat_optional_vies-14.0.2.1.0.dist-info/RECORD
